silkworm/__init__.py
silkworm/_types.py
silkworm/api.py
silkworm/cdp.py
silkworm/engine.py
silkworm/exceptions.py
silkworm/http.py
silkworm/logging.py
silkworm/middlewares.py
silkworm/pipelines.py
silkworm/request.py
silkworm/response.py
silkworm/runner.py
silkworm/spiders.py
silkworm/py.typed
silkworm_rs-0.2.38.dist-info/METADATA
silkworm_rs-0.2.38.dist-info/WHEEL
silkworm_rs-0.2.38.dist-info/licenses/LICENSE
silkworm_rs-0.2.38.dist-info/RECORD
