Metadata-Version: 2.4
Name: silkworm-rs
Version: 0.2.38
Summary: Async-first web scraping framework built on rnet and scraper-rs
Project-URL: Homepage, https://github.com/BitingSnakes/silkworm
Project-URL: Repository, https://github.com/BitingSnakes/silkworm
Project-URL: Issues, https://github.com/BitingSnakes/silkworm/issues
Author-email: Yehor Smoliakov <egorsmkv@gmail.com>
License: MIT License
License-File: LICENSE
Keywords: asyncio,crawler,html,http,spider,web-scraping
Classifier: Development Status :: 5 - Production/Stable
Classifier: Intended Audience :: Developers
Classifier: License :: OSI Approved :: MIT License
Classifier: Programming Language :: Python :: 3
Classifier: Programming Language :: Python :: 3 :: Only
Classifier: Programming Language :: Python :: 3.13
Classifier: Programming Language :: Python :: 3.14
Classifier: Topic :: Internet :: WWW/HTTP
Classifier: Topic :: Internet :: WWW/HTTP :: Indexing/Search
Classifier: Topic :: Software Development :: Libraries
Classifier: Typing :: Typed
Requires-Python: <3.15,>=3.13
Requires-Dist: charset-normalizer==3.4.4
Requires-Dist: logly==0.1.6
Requires-Dist: rnet==3.0.0rc17
Requires-Dist: rxml==2.3.6
Requires-Dist: scraper-rust==0.2.27
Provides-Extra: avro
Requires-Dist: fastavro==1.12.1; extra == 'avro'
Provides-Extra: cassandra
Requires-Dist: cassandra-driver==3.29.3; extra == 'cassandra'
Provides-Extra: cdp
Requires-Dist: websockets==16.0; extra == 'cdp'
Provides-Extra: couchdb
Requires-Dist: aiocouch==4.0.1; extra == 'couchdb'
Provides-Extra: duckdb
Requires-Dist: duckdb==1.4.3; extra == 'duckdb'
Provides-Extra: dynamodb
Requires-Dist: aioboto3==15.5.0; extra == 'dynamodb'
Provides-Extra: elasticsearch
Requires-Dist: elasticsearch==9.2.1; extra == 'elasticsearch'
Provides-Extra: excel
Requires-Dist: openpyxl==3.1.5; extra == 'excel'
Provides-Extra: ftp
Requires-Dist: aioftp==0.27.2; extra == 'ftp'
Provides-Extra: gsheets
Requires-Dist: google-api-python-client==2.187.0; extra == 'gsheets'
Requires-Dist: google-auth==2.47.0; extra == 'gsheets'
Provides-Extra: memray
Requires-Dist: memray==1.19.1; extra == 'memray'
Provides-Extra: mongodb
Requires-Dist: motor==3.7.1; extra == 'mongodb'
Provides-Extra: msgpack
Requires-Dist: ormsgpack==1.12.1; extra == 'msgpack'
Provides-Extra: mysql
Requires-Dist: aiomysql==0.3.2; extra == 'mysql'
Provides-Extra: polars
Requires-Dist: polars==1.36.1; extra == 'polars'
Provides-Extra: postgresql
Requires-Dist: asyncpg==0.31.0; extra == 'postgresql'
Provides-Extra: s3
Requires-Dist: opendal==0.46.0; extra == 's3'
Provides-Extra: sftp
Requires-Dist: asyncssh==2.22.0; extra == 'sftp'
Provides-Extra: snowflake
Requires-Dist: snowflake-connector-python==4.1.1; extra == 'snowflake'
Provides-Extra: taskiq
Requires-Dist: taskiq==0.12.1; extra == 'taskiq'
Provides-Extra: trio
Requires-Dist: trio-asyncio==0.15.0; extra == 'trio'
Requires-Dist: trio==0.32.0; extra == 'trio'
Provides-Extra: uvloop
Requires-Dist: uvloop==0.22.1; extra == 'uvloop'
Provides-Extra: vortex
Requires-Dist: vortex-data==0.58.0; extra == 'vortex'
Provides-Extra: winloop
Requires-Dist: winloop==0.4.1; extra == 'winloop'
Provides-Extra: yaml
Requires-Dist: pyyaml==6.0.3; extra == 'yaml'
